{"type":"article","slug":"mic/content/153/5/1546","journal":"mic","canonical":"https://www.sgmjournals.org/mic/content/153/5/1546","meta":{"title":"A two-component small multidrug resistance pump functions as a metabolic valve during nicotine catabolism by Arthrobacter nicotinovorans","authors":["Ganas, Petra","Mihasan, Marius","Igloi, Gabor L.","Brandsch, Roderich"],"journalTitle":"Microbiology","journalAbbrev":"","volume":"153","issue":"5","firstpage":"1546","lastpage":"","date":"05/01/2007","doi":"10.1099/mic.0.2006/004234-0","issn":[],"pmid":"17464069","mjid":"mic;153/5/1546","section":"","abstractUrl":"http://mic.sgmjournals.org/cgi/content/abstract/153/5/1546","fulltextUrl":"http://mic.sgmjournals.org/cgi/content/full/153/5/1546","pdfUrl":"http://mic.sgmjournals.org/cgi/reprint/153/5/1546.pdf","publicUrl":""},"abstractHtml":"","bodyHtml":"","referencesHtml":"","affiliationsHtml":"","correspHtml":"","pdfPath":null,"refdomains":1}