{"type":"article","slug":"mic/content/141/11/2793","journal":"mic","canonical":"https://www.sgmjournals.org/mic/content/141/11/2793","meta":{"title":"Amplification of 16S ribosomal RNA genes of autotrophic ammonia-oxidizing bacteria demonstrates the ubiquity of nitrosospiras in the environment","authors":["Hiorns, William D.","Hastings, Richard C.","Head, Ian M.","McCarthy, Alan J.","Saunders, Jon R.","Pickup, Roger W.","Hall, Grahame H."],"journalTitle":"Microbiology","journalAbbrev":"","volume":"141","issue":"11","firstpage":"2793","lastpage":"","date":"11/01/1995","doi":"10.1099/13500872-141-11-2793","issn":[],"pmid":"8535507","mjid":"mic;141/11/2793","section":"","abstractUrl":"http://mic.sgmjournals.org/cgi/content/abstract/141/11/2793","fulltextUrl":"","pdfUrl":"http://mic.sgmjournals.org/cgi/reprint/141/11/2793.pdf","publicUrl":""},"abstractHtml":"<p>Summary: Oligonucleotide sequences selected from the 16S rRNA genes of various species of ammonia-oxidizing bacteria were evaluated as specific PCR amplification primers and probes. The specificities of primer pairs for eubacterial, <i>Nitrosospira</i> and <i>Nitrosomonas</i> rRNA genes were established with sequence databases, and the primer pairs were used to amplify DNA from laboratory cultures and environmental samples. Eubacterial rRNA genes amplified from samples of soil and activated sludge hybridized with an oligonucleotide probe specific for <i>Nitrosospira</i> spp., but not with a <i>Nitrosomonas</i>-specific probe. Lakewater and sediment samples were analysed using a nested PCR technique in which eubacterial rRNA genes were subjected to a secondary amplification with <i>Nitrosomonas</i> or <i>Nitrosospira</i> specific primers. Again, the presence of <i>Nitrosospira</i> DNA, but not <i>Nitrosomonas</i> DNA, was detected and this was confirmed by hybridization of the amplified DNA with an internal oligonucleotide probe. Enrichments of lakewater and sediment samples, incubated for two weeks in the presence of ammonium, produced nitrite and were found to contain DNA from both <i>Nitrosospira</i> and <i>Nitrosomonas</i> as determined by nested PCR amplification and probing of 16S rRNA genes. This demonstrates that <i>Nitrosospira</i> spp. are widespread in the environment. The implications of the detection of <i>Nitrosomonas</i> DNA only after enrichment culture are discussed.</p>","bodyHtml":"","referencesHtml":"","affiliationsHtml":"","correspHtml":"","pdfPath":null,"summaryHtml":"","ccTier":"tier3-abstract","refdomains":0}