{"type":"article","slug":"vir/content/37/1/221","journal":"vir","canonical":"https://www.sgmjournals.org/vir/content/37/1/221","meta":{"title":"Repeated 'Superinduction' of Interferon in Human Diploid Fibroblast Cultures","authors":["Wiranowska-Stewart, Marzenna","Chudzio, T.","Stewart, W. E., II"],"journalTitle":"Journal of General Virology","journalAbbrev":"","volume":"37","issue":"1","firstpage":"221","lastpage":"","date":"10/01/1977","doi":"10.1099/0022-1317-37-1-221","issn":[],"pmid":"915483","mjid":"vir;37/1/221","section":"","abstractUrl":"http://vir.sgmjournals.org/cgi/content/abstract/37/1/221","fulltextUrl":"","pdfUrl":"http://vir.sgmjournals.org/cgi/reprint/37/1/221.pdf","publicUrl":""},"abstractHtml":"<p>Human diploid fibroblast cultures induced to make interferon by the combination of polyriboinosinic acid-polyribocytidylic acid, cycloheximide and actinomycin D degenerate thereafter, owing to the irreversible nature of the inhibition induced by actinomycin D. However, cultures superinduced with the DNA-dependent RNA synthesis inhibitor 5,6-dichloro-1--D-ribofuranosylbenzimidazole (DRB) survive, owing to the reversible nature of the inhibition induced by DRB, and can again be superinduced on several occasions.</p>","bodyHtml":"","referencesHtml":"","affiliationsHtml":"","correspHtml":"","pdfPath":null,"summaryHtml":"","ccTier":"tier3-abstract","refdomains":0}