{"type":"article","slug":"vir/content/65/2/429","journal":"vir","canonical":"https://www.sgmjournals.org/vir/content/65/2/429","meta":{"title":"Friend Erythroleukaemia Cell Mutants Defective in Viral Gene Expression","authors":["Yokota, J.","Iwamoto, A.","Suzuki, Atsuko","Yamaguchi-Tejima, Sachiko","Kitamura, Y.","Yoshikura, H."],"journalTitle":"Journal of General Virology","journalAbbrev":"","volume":"65","issue":"2","firstpage":"429","lastpage":"","date":"02/01/1984","doi":"10.1099/0022-1317-65-2-429","issn":[],"pmid":"6693859","mjid":"vir;65/2/429","section":"","abstractUrl":"http://vir.sgmjournals.org/cgi/content/abstract/65/2/429","fulltextUrl":"","pdfUrl":"http://vir.sgmjournals.org/cgi/reprint/65/2/429.pdf","publicUrl":""},"abstractHtml":"<p>Cellular mutants defective in the expression of viral polypeptides were isolated from the Friend erythroleukaemia cell line 745a by immunoselection with anti-ecotropic murine leukaemia virus serum in the presence of complement. The mode of appearance of the antiserum-resistant cells showed an interesting pattern which is discussed in the text. One of the mutants obtained contained no detectable gp70 or p15(E) while retaining gPr90<sup>env</sup>; defects appeared to reside in the processing of the gPr90<sup>env</sup> to gp70 and p15(E). In another type of mutant, gPr90<sup>env</sup> was not detected. All these mutants retained spleen focus-forming virus (SFFV)-specific gp55 and <i>gag</i> precursor Pr68<sup>gag</sup>. The mutants superinfected with the helper virus produced the helper and SFFV also, indicating that these mutations did not affect the replication of the exogenously infecting virus.</p>","bodyHtml":"","referencesHtml":"","affiliationsHtml":"","correspHtml":"","pdfPath":null,"summaryHtml":"","ccTier":"tier3-abstract","refdomains":0}