{"type":"article","slug":"mic/content/146/10/2425","journal":"mic","canonical":"https://www.sgmjournals.org/mic/content/146/10/2425","meta":{"title":"Vanadium interferes with siderophore-mediated iron uptake in Pseudomonas aeruginosa","authors":["Baysse, Christine","De Vos, Daniel","Naudet, Yann","Vandermonde, Alain","Ochsner, Urs","Meyer, Jean-Marie","Budzikiewicz, Herbert","Schafer, Matthias","Fuchs, Regine","Cornelis, Pierre"],"journalTitle":"Microbiology","journalAbbrev":"","volume":"146","issue":"10","firstpage":"2425","lastpage":"","date":"10/01/2000","doi":"","issn":[],"pmid":"11021919","mjid":"mic;146/10/2425","section":"","abstractUrl":"http://mic.sgmjournals.org/cgi/content/abstract/146/10/2425","fulltextUrl":"http://mic.sgmjournals.org/cgi/content/full/146/10/2425","pdfUrl":"http://mic.sgmjournals.org/cgi/reprint/146/10/2425.pdf","publicUrl":""},"abstractHtml":"","bodyHtml":"","referencesHtml":"","affiliationsHtml":"","correspHtml":"","pdfPath":null,"refdomains":1}