{"type":"article","slug":"vir/content/69/5/1111","journal":"vir","canonical":"https://www.sgmjournals.org/vir/content/69/5/1111","meta":{"title":"The Global Spread and Replacement of Canine Parvovirus Strains","authors":["Parrish, Colin R.","Have, Per","Foreyt, William J.","Evermann, James F.","Senda, Megumi","Carmichael, Leland E."],"journalTitle":"Journal of General Virology","journalAbbrev":"","volume":"69","issue":"5","firstpage":"1111","lastpage":"","date":"05/01/1988","doi":"10.1099/0022-1317-69-5-1111","issn":[],"pmid":"2836554","mjid":"vir;69/5/1111","section":"","abstractUrl":"http://vir.sgmjournals.org/cgi/content/abstract/69/5/1111","fulltextUrl":"","pdfUrl":"http://vir.sgmjournals.org/cgi/reprint/69/5/1111.pdf","publicUrl":""},"abstractHtml":"<p><sup><sup>1</sup></sup> James A. Baker Institute, New York State College of Veterinary Medicine, Cornell University, Ithaca, New York 14853, U.S.A.<br> <sup><sup>2</sup></sup> State Veterinary Institute for Virus Research, Lindholm, 4771 Kalvehave, Denmark<br> <sup><sup>3</sup></sup> Department of Veterinary Microbiology and Pathology, College of Veterinary Medicine, Washington State University, Pullman, Washington 99164, U.S.A.<br> <sup><sup>4</sup></sup> Department of Veterinary Clinical Medicine and Surgery and Washington Animal Disease Diagnostic Laboratory, College of Veterinary Medicine, Washington State University, Pullman, Washington 99164, U.S.A.<br> and<sup><sup>5</sup></sup> National Veterinary Assay Laboratory, Ministry of Agriculture, Forestry and Fisheries, 1-15-1 Tokura, Kokubunji, Tokyo 185, Japan</p>\n<p>Canine parvovirus type 2 (CPV-2) became widespread during 1978 and was reported in many countries during 1978 and 1979. Earlier studies showed that CPV-2 was replaced in the U.S.A. around 1980 by an antigenically and genetically variant virus (CPV-2a). Here we show that CPV-2 was present in the U.S.A., Japan, Belgium and Australia prior to 1980, but that between 1979 and 1982 CPV-2 was replaced by CPV-2a in all of those countries as well as in France and Denmark. Examination of sera collected between 1979 and 1984 from wild coyotes (<i>Canis latrans</i>) in the U.S.A. by an agar gel precipitin assay indicated that the coyotes were originally infected by CPV-2, but that after 1980 the juvenile coyotes were being infected with CPV-2a. The natural global replacement of CPV-2 by CPV-2a over a period of 2 to 3 years indicates that CPV-2a has a strong epidemiological advantage over CPV-2, although the mechanism involved remains to be defined.</p>","bodyHtml":"","referencesHtml":"","affiliationsHtml":"","correspHtml":"","pdfPath":null,"summaryHtml":"","ccTier":"tier3-abstract","refdomains":0}