{"type":"article","slug":"ijs/content/55/3/1315","journal":"ijs","canonical":"https://www.sgmjournals.org/ijs/content/55/3/1315","meta":{"title":"Pedobacter caeni sp. nov., a novel species isolated from a nitrifying inoculum","authors":["Vanparys, Bram","Heylen, Kim","Lebbe, Liesbeth","De Vos, Paul"],"journalTitle":"International Journal of Systematic and Evolutionary Microbiology","journalAbbrev":"","volume":"55","issue":"3","firstpage":"1315","lastpage":"","date":"05/01/2005","doi":"10.1099/ijs.0.63635-0","issn":[],"pmid":"15879274","mjid":"ijs;55/3/1315","section":"","abstractUrl":"http://ijs.sgmjournals.org/cgi/content/abstract/55/3/1315","fulltextUrl":"http://ijs.sgmjournals.org/cgi/content/full/55/3/1315","pdfUrl":"http://ijs.sgmjournals.org/cgi/reprint/55/3/1315.pdf","publicUrl":""},"abstractHtml":"<p>A Gram-negative, rod-shaped, non-spore-forming bacterium was isolated from a nitrifying inoculum. On the basis of 16S rRNA gene sequence similarity, LMG 22862<sup>T</sup> was shown to belong to the family <i>Sphingobacteriaceae</i>, related to <i>Pedobacter africanus</i> (98·0 %) and <i>Pedobacter heparinus</i> (97·6 %). The results of 16S rRNA gene sequence analysis, DNADNA hybridization, SDS-PAGE, analysis of the fatty acid composition and physiological and biochemical tests allowed genotypic and phenotypic differentiation of LMG 22862<sup>T</sup> from <i>Pedobacter</i> species with validly published names. LMG 22862<sup>T</sup> therefore represents a novel species within this genus, for which the name <i>Pedobacter caeni</i> sp. nov. is proposed, with the type strain LMG 22862<sup>T</sup> (=DSM 16990<sup>T</sup>).</p>","bodyHtml":"","referencesHtml":"","affiliationsHtml":"","correspHtml":"","pdfPath":null,"summaryHtml":"","ccTier":"tier3-abstract","refdomains":0}