{"type":"article","slug":"vir/content/36/1/151.full.pdf","journal":"vir","canonical":"https://www.sgmjournals.org/vir/content/36/1/151","meta":{"title":"Further Studies on the Activation of Influenza Virus by Proteolytic Cleavage of the Haemagglutinin","authors":[],"journalTitle":"Journal of General Virology","journalAbbrev":"","volume":"36","issue":"1","firstpage":"151","lastpage":"","date":"07/01/1977","doi":"10.1099/0022-1317-36-1-151","issn":[],"pmid":"142124","mjid":"vir;36/1/151","section":"","abstractUrl":"http://vir.sgmjournals.org/cgi/content/abstract/36/1/151","fulltextUrl":"","pdfUrl":"http://vir.sgmjournals.org/cgi/reprint/36/1/151.pdf","publicUrl":""},"abstractHtml":"","bodyHtml":"","referencesHtml":"","affiliationsHtml":"","correspHtml":"","pdfPath":null,"refdomains":1,"alias":true}