{"type":"article","slug":"jmm/content/9/3/325","journal":"jmm","canonical":"https://www.sgmjournals.org/jmm/content/9/3/325","meta":{"title":"Bifidobacteria in the intestinal tract of infants: an in-vivo study","authors":["BULLEN, C. L.","TEARLE, P. V.","WILLIS, A. T."],"journalTitle":"Journal of Medical Microbiology","journalAbbrev":"","volume":"9","issue":"3","firstpage":"325","lastpage":"","date":"08/01/1976","doi":"10.1099/00222615-9-3-325","issn":[],"pmid":"8646","mjid":"medmicro;9/3/325","section":"","abstractUrl":"http://jmm.sgmjournals.org/cgi/content/abstract/9/3/325","fulltextUrl":"","pdfUrl":"http://jmm.sgmjournals.org/cgi/reprint/9/3/325.pdf","publicUrl":""},"abstractHtml":"<p>A buffer consisting of acetic acid and acetate was demonstrated in the faeces of all the breast-fed infants at some time during the period of examination. This buffer was rarely detected during the 1st week of life when supplementary feeds were given, and buffer already present gradually disappeared with the introduction of mixed feeding. In contrast, at no time was an acetate buffer demonstrated in the faeces of bottle-fed infants. Babies receiving breast milk produced faeces with low <i>pH</i>, high counts of saccharolytic organisms including bifidobacteria and <i>Streptococcus faecium</i>, and low counts of <i>Escherichia coli</i>, bacteroides and clostridia. Bottle-fed infants on the other hand produced faeces with a high <i>pH</i> and high counts of <i>E. coli</i> and putrefactive bacteria, but with low counts of bifidobacteria.</p>","bodyHtml":"","referencesHtml":"","affiliationsHtml":"","correspHtml":"","pdfPath":null,"summaryHtml":"","ccTier":"tier3-abstract","refdomains":0}