{"type":"article","slug":"vir/content/66/12/2533","journal":"vir","canonical":"https://www.sgmjournals.org/vir/content/66/12/2533","meta":{"title":"Cytotoxic Lymphocytes in the Lungs of Mice Infected with Respiratory Syncytial Virus","authors":["Taylor, G.","Stott, E. J.","Hayle, A. J."],"journalTitle":"Journal of General Virology","journalAbbrev":"","volume":"66","issue":"12","firstpage":"2533","lastpage":"","date":"12/01/1985","doi":"10.1099/0022-1317-66-12-2533","issn":[],"pmid":"2866227","mjid":"vir;66/12/2533","section":"","abstractUrl":"http://vir.sgmjournals.org/cgi/content/abstract/66/12/2533","fulltextUrl":"","pdfUrl":"http://vir.sgmjournals.org/cgi/reprint/66/12/2533.pdf","publicUrl":""},"abstractHtml":"<p>Mice infected with respiratory syncytial virus (RSV) developed cytotoxic lymphocytes in the lungs, which lysed RSV-infected, but not uninfected cells. Cytotoxic activity was greatest 7 to 9 days after infection, was virus-specific, MHC-restricted and abolished by treatment of lymphocytes with anti-Thy 1.2 or with anti-Lyt 2.2 sera and complement. There was a close temporal relationship between the appearance of these cytotoxic lymphocytes in the lung and clearance of virus. In contrast, RSV persisted in the lungs of athymic (nude) mice and such animals failed to develop RSV-specific cytotoxic lymphocytes. Thus, cytotoxic T-cells may have an important role in recovery from RSV infection.</p>","bodyHtml":"","referencesHtml":"","affiliationsHtml":"","correspHtml":"","pdfPath":null,"summaryHtml":"","ccTier":"tier3-abstract","refdomains":0}