{"type":"article","slug":"vir/content/67/11/2539","journal":"vir","canonical":"https://www.sgmjournals.org/vir/content/67/11/2539","meta":{"title":"Antibody-mediated Early Death in vivo after Infection with Yellow Fever Virus","authors":["Barrett, A. D. T.","Gould, E. A."],"journalTitle":"Journal of General Virology","journalAbbrev":"","volume":"67","issue":"11","firstpage":"2539","lastpage":"","date":"11/01/1986","doi":"10.1099/0022-1317-67-11-2539","issn":[],"pmid":"3783130","mjid":"vir;67/11/2539","section":"","abstractUrl":"http://vir.sgmjournals.org/cgi/content/abstract/67/11/2539","fulltextUrl":"","pdfUrl":"http://vir.sgmjournals.org/cgi/reprint/67/11/2539.pdf","publicUrl":""},"abstractHtml":"<p>The phenomenon known as antibody-dependent enhancement (ADE) has been demonstrated <i>in vitro</i> but its significance in viral pathogenesis is uncertain even though it has been associated with dengue shock syndrome. Here we report for the first time the enhancement of virus virulence in mice using monoclonal antibodies (MAbs) prepared against yellow fever (YF) viruses. Our results show that the average survival time of mice was reduced by up to 33% (i.e. 6.7 to 4.5 days) and that ADE is both antibody dose-dependent and antibody- and virus strain-specific. A total of 12 YF viruses and 11 MAbs were examined and of these only three YF viruses (FNV, Asibi and B11) could be enhanced <i>in vivo</i> by only two MAbs (427 and 126). A particular combination of virus and antibody is required for ADE to take place.</p>","bodyHtml":"","referencesHtml":"","affiliationsHtml":"","correspHtml":"","pdfPath":null,"summaryHtml":"","ccTier":"tier3-abstract","refdomains":0}