{"type":"article","slug":"vir/content/78/2/291.full.pdf+html","journal":"vir","canonical":"https://www.sgmjournals.org/vir/content/78/2/291","meta":{"title":"The molecular biology of caliciviruses","authors":[],"journalTitle":"Journal of General Virology","journalAbbrev":"","volume":"78","issue":"2","firstpage":"291","lastpage":"","date":"02/01/1997","doi":"","issn":[],"pmid":"9018049","mjid":"","section":"","abstractUrl":"","fulltextUrl":"","pdfUrl":"http://vir.sgmjournals.org/cgi/reprint/78/2/291.pdf","publicUrl":""},"abstractHtml":"","bodyHtml":"","referencesHtml":"","affiliationsHtml":"","correspHtml":"","pdfPath":null,"refdomains":2,"alias":true}