{"type":"article","slug":"vir/content/64/4/927","journal":"vir","canonical":"https://www.sgmjournals.org/vir/content/64/4/927","meta":{"title":"Infrequent Transmission of Double-stranded RNA Virus Particles but Absence of DNA Proviruses in Single Ascospore Cultures of Gaeumannomyces graminis","authors":["McFadden, J. J. P.","Buck, K. W.","Rawlinson, C. J."],"journalTitle":"Journal of General Virology","journalAbbrev":"","volume":"64","issue":"4","firstpage":"927","lastpage":"","date":"04/01/1983","doi":"10.1099/0022-1317-64-4-927","issn":[],"pmid":"","mjid":"vir;64/4/927","section":"","abstractUrl":"http://vir.sgmjournals.org/cgi/content/abstract/64/4/927","fulltextUrl":"","pdfUrl":"http://vir.sgmjournals.org/cgi/reprint/64/4/927.pdf","publicUrl":""},"abstractHtml":"<p>A field isolate, 3b1a, of the wheat take-all fungus <i>Gaeumannomyces graminis</i> var. <i>tritici</i>, was previously shown to be infected with three serologically unrelated viruses, A, B, and C. It is now shown that virus B can be separated into two distinct strains, designated B1 and B2. All four viruses, A, B1, B2 and C, were faithfully transmitted into conidia. However, six out of eight single ascospore cultures derived from 3b1a single conidial cultures were shown to be virus-free. The remaining two single ascospore cultures each contained only one virus, which appeared to be the same in each culture. This virus was serologically indistinguishable from virus B1, but had dsRNA components of mol. wt. lower than those of virus B1 and had only the smaller of the two capsid polypeptide species of virus B1. No DNA provirus molecules homologous to viruses B1, B2 or C could be detected in two of the virus-free ascospore cultures or in one of the virus-infected ascospore cultures. Very low concentrations of virus particles were detected in hyphal tip isolates of <i>G. graminis</i>. After prolonged storage and subculturing of these isolates, the concentration of virus particles had increased to the level of the parent culture from which the hyphal tip isolates were derived.</p>","bodyHtml":"","referencesHtml":"","affiliationsHtml":"","correspHtml":"","pdfPath":null,"summaryHtml":"","ccTier":"tier3-abstract","refdomains":0}