{"type":"article","slug":"jmm/content/16/1/61","journal":"jmm","canonical":"https://www.sgmjournals.org/jmm/content/16/1/61","meta":{"title":"Effect of glucose concentration in the growth medium upon neutral and acidic fermentation end-products of Clostridium bifermentans, Clostridium sporogenes and peptostreptococcus anaerobius","authors":["Turton, L. J.","Drucker, D. B.","Ganguli, L. A."],"journalTitle":"Journal of Medical Microbiology","journalAbbrev":"","volume":"16","issue":"1","firstpage":"61","lastpage":"","date":"02/01/1983","doi":"","issn":[],"pmid":"6822993","mjid":"medmicro;16/1/61","section":"","abstractUrl":"http://jmm.sgmjournals.org/cgi/content/abstract/16/1/61","fulltextUrl":"","pdfUrl":"","publicUrl":""},"abstractHtml":"<p>Clostridium bifermentans, C. sporogenes and Peptostreptococcus anaerobius were grown in Fastidious Anaerobe Broth with glucose concentrations from 0-1.5% (w/v). Gas chromatographic (GLC) analysis of fermentation end-products revealed that a change in glucose concentration markedly affected fermentation patterns of each microorganism. Increased glucose concentration resulted in stimulation of ethanol production by all strains, and of butanol and butyric acid by C. sporogenes. With C. bifermentans, there was a parallel increase in ethanol and acetic acid production and decreased formation of propanol and propionic, iso-butyric and iso-valeric acids. Increased ethanol formation by P. anaerobius was accompanied by an increase in acetic acid and a decrease in butan-1-ol production. The greatest incremental change in GLC profiles occurred when glucose concentration was raised from zero to 0.1% (w/v). These data suggest that glucose concentration in a medium for GLC analysis must be rigorously controlled if reproducible results are to be obtained.<br clear=\"all\"> <br clear=\"all\"> <br clear=\"all\"> <br clear=\"all\"> <br clear=\"all\"></p>","bodyHtml":"","referencesHtml":"","affiliationsHtml":"","correspHtml":"","pdfPath":null,"summaryHtml":"","ccTier":"tier3-abstract","refdomains":0}