{"type":"article","slug":"ijs/content/58/11/2505","journal":"ijs","canonical":"https://www.sgmjournals.org/ijs/content/58/11/2505","meta":{"title":"Description of Croceitalea gen. nov. in the family Flavobacteriaceae with two species, Croceitalea eckloniae sp. nov. and Croceitalea dokdonensis sp. nov., isolated from the rhizosphere of the marine alga Ecklonia kurome","authors":["Lee, Hee-Soon","Kwon, Kae Kyoung","Yang, Sung-Hyun","Bae, Seung Seob","Park, Chan Hong","Kim, Sang-Jin","Lee, Jung-Hyun"],"journalTitle":"International Journal of Systematic and Evolutionary Microbiology","journalAbbrev":"","volume":"58","issue":"11","firstpage":"2505","lastpage":"","date":"11/01/2008","doi":"10.1099/ijs.0.65697-0","issn":[],"pmid":"18984684","mjid":"ijs;58/11/2505","section":"","abstractUrl":"http://ijs.sgmjournals.org/cgi/content/abstract/58/11/2505","fulltextUrl":"http://ijs.sgmjournals.org/cgi/content/full/58/11/2505","pdfUrl":"http://ijs.sgmjournals.org/cgi/reprint/58/11/2505.pdf","publicUrl":""},"abstractHtml":"<p>Two novel bacterial strains, designated DOKDO 025<sup>T</sup> and DOKDO 023<sup>T</sup>, were isolated on Dokdo Island, Korea, from the rhizosphere of the brown alga <i>Ecklonia kurome</i>. The strains were subjected to a polyphasic taxonomy study and were found to be Gram-negative, aerobic, rod-shaped, non-motile and orange-coloured. The isolates shared 96.3 % 16S rRNA gene sequence similarity. They showed 93.8–95.6 % 16S rRNA gene sequence similarity with respect to members of the genus <i>Muricauda</i> in the family <i>Flavobacteriaceae</i>, but formed a distinct phyletic line. Moreover, the cellular appendages reported for all <i>Muricauda</i> species were absent from strains DOKDO 025<sup>T</sup> and DOKDO 023<sup>T</sup>. The predominant cellular fatty acids of strain DOKDO 025<sup>T</sup> were iso-C<sub>15 : 0</sub>, iso-C<sub>15 : 1</sub> and one with an equivalent chain-length of 13.565 and those of strain DOKDO 023<sup>T</sup> were iso-C<sub>15 : 0</sub>, iso-C<sub>15 : 1</sub> and iso-C<sub>17 : 0</sub> 3-OH. The DNA G+C content of strains DOKDO 025<sup>T</sup> and DOKDO 023<sup>T</sup> were 59.5 and 66.5 mol%, respectively, higher than any values found in recognized members of the family <i>Flavobacteriaceae</i>. The major respiratory quinone was MK-6. On the basis of evidence from the polyphasic study, strains DOKDO 025<sup>T</sup> and DOKDO 023<sup>T</sup> represent two novel species in a new genus, <i>Croceitalea</i> gen. nov., for which the names <i>Croceitalea eckloniae</i> sp. nov. (the type species) and <i>Croceitalea dokdonensis</i> sp. nov. are proposed. The type strain of <i>Croceitalea eckloniae</i> sp. nov. is DOKDO 025<sup>T</sup> (=KCCM 42309<sup>T</sup> =JCM 13827<sup>T</sup>) and that of <i>Croceitalea dokdonensis</i> sp. nov. is DOKDO 023<sup>T</sup> (=KCCM 42308<sup>T</sup> =JCM 13826<sup>T</sup>).</p>","bodyHtml":"","referencesHtml":"","affiliationsHtml":"","correspHtml":"","pdfPath":null,"summaryHtml":"","ccTier":"tier3-abstract","refdomains":0}