{"type":"article","slug":"jmm/content/37/3/206","journal":"jmm","canonical":"https://www.sgmjournals.org/jmm/content/37/3/206","meta":{"title":"Correlation between cytotoxin production and sporulation in Clostridium difficile","authors":["Kamiya, S.","Ogura, H.","Meng, X. Q.","Nakamura, S."],"journalTitle":"Journal of Medical Microbiology","journalAbbrev":"","volume":"37","issue":"3","firstpage":"206","lastpage":"","date":"09/01/1992","doi":"","issn":[],"pmid":"1518037","mjid":"medmicro;37/3/206","section":"","abstractUrl":"http://jmm.sgmjournals.org/cgi/content/abstract/37/3/206","fulltextUrl":"","pdfUrl":"","publicUrl":""},"abstractHtml":"<p>Correlation between cytotoxin production and sporulation was demonstrated when a Clostridium difficile culture was inoculated into fresh broth to give an initial count of less than 10 vegetative cells/ml with no spores. Under these conditions, cytotoxin was produced and released during sporulation. Addition of a sporulation inhibitor (acridine orange, 30 mg/L), resulted in a marked decrease in both sporulation and cytotoxin production, despite there being no change in the number of vegetative cells in the culture. These results indicate that sporulation might be closely related to cytotoxin production.<br clear=\"all\"> <br clear=\"all\"> <br clear=\"all\"></p>","bodyHtml":"","referencesHtml":"","affiliationsHtml":"","correspHtml":"","pdfPath":null,"summaryHtml":"","ccTier":"tier3-abstract","refdomains":0}