{"type":"article","slug":"vir/content/65/4/795","journal":"vir","canonical":"https://www.sgmjournals.org/vir/content/65/4/795","meta":{"title":"Newcastle Disease Virus: the Effect of Monoclonal Antibody in the Overlay on Virus Penetration and the Immunoselection of Variants","authors":["Russell, Peter H."],"journalTitle":"Journal of General Virology","journalAbbrev":"","volume":"65","issue":"4","firstpage":"795","lastpage":"","date":"04/01/1984","doi":"10.1099/0022-1317-65-4-795","issn":[],"pmid":"6546769","mjid":"vir;65/4/795","section":"","abstractUrl":"http://vir.sgmjournals.org/cgi/content/abstract/65/4/795","fulltextUrl":"","pdfUrl":"http://vir.sgmjournals.org/cgi/reprint/65/4/795.pdf","publicUrl":""},"abstractHtml":"<p>Monoclonal antibody to the haemagglutininneuraminidase or the fusion glycoprotein of Newcastle disease virus blocked virus penetration which otherwise occurred within 90 s of the temperature being increased from 4 °C to 37 °C. These antibodies regularly immunoselected variant plaques only when incorporated into the agarose overlay. Variant viruses then formed plaques whereas the growth of non-neutralized normal virus was suppressed.</p>","bodyHtml":"","referencesHtml":"","affiliationsHtml":"","correspHtml":"","pdfPath":null,"summaryHtml":"","ccTier":"tier3-abstract","refdomains":0}