{"type":"article","slug":"jmm/content/58/8/1045","journal":"jmm","canonical":"https://www.sgmjournals.org/jmm/content/58/8/1045","meta":{"title":"A new multiplex PCR-based reverse line-blot hybridization (mPCR/RLB) assay for rapid staphylococcal cassette chromosome mec (SCCmec) typing","authors":["Cai, Lin","Kong, Fanrong","Wang, Qinning","Wang, Huiping","Xiao, Meng","Sintchenko, Vitali","Gilbert, Gwendolyn L."],"journalTitle":"Journal of Medical Microbiology","journalAbbrev":"","volume":"58","issue":"8","firstpage":"1045","lastpage":"","date":"08/01/2009","doi":"10.1099/jmm.0.007955-0","issn":[],"pmid":"19528184","mjid":"medmicro;58/8/1045","section":"","abstractUrl":"http://jmm.sgmjournals.org/cgi/content/abstract/58/8/1045","fulltextUrl":"http://jmm.sgmjournals.org/cgi/content/full/58/8/1045","pdfUrl":"http://jmm.sgmjournals.org/cgi/reprint/58/8/1045.pdf","publicUrl":""},"abstractHtml":"<p><sup>1</sup> Department of Dermatology, Peking University People's Hospital, Beijing 100044, PR China<br> <br> <sup>2</sup> Centre for Infectious Diseases and Microbiology, Institute of Clinical Pathology and Medical Research (ICPMR), Westmead, New South Wales, Australia<br> <br> <sup>3</sup> Department of Dermatology, Tianjin Medical University General Hospital, Tianjin, PR China<br> <br> <sup>4</sup> Life Science College, Peking University, Beijing, PR China<br> <br> <sup>5</sup> Western Clinical School, University of Sydney, Sydney, Australia</p>\n<p><b>Correspondence</b> <br> Gwendolyn L. Gilbert <br> <span>l.gilbert{at}usyd.edu.au</span></p>","bodyHtml":"","referencesHtml":"","affiliationsHtml":"","correspHtml":"","pdfPath":null,"summaryHtml":"","ccTier":"tier3-abstract","refdomains":0}